<?xml version="1.0" encoding="UTF-8" ?>
<!DOCTYPE mapper PUBLIC "-//mybatis.org//DTD Mapper 3.0//EN" "http://mybatis.org/dtd/mybatis-3-mapper.dtd" >
<mapper namespace="cn.creditease.godzilla.dao.ProjPrivateMapper" >
  <resultMap id="BaseResultMap" type="cn.creditease.godzilla.model.ProjPrivate" >
    <!--
      WARNING - @mbggenerated
      This element is automatically generated by MyBatis Generator, do not modify.
      This element was generated on Wed Jun 10 19:29:50 CST 2015.
    -->
    <result column="id" property="id" jdbcType="CHAR" />
    <result column="user_name" property="userName" jdbcType="VARCHAR" />
    <result column="project_code" property="projectCode" jdbcType="VARCHAR" />
    <result column="virtual_truck_url" property="virtualTruckUrl" jdbcType="VARCHAR" />
  </resultMap>
  <insert id="insert" parameterType="cn.creditease.godzilla.model.ProjPrivate" >
    <!--
      WARNING - @mbggenerated
      This element is automatically generated by MyBatis Generator, do not modify.
      This element was generated on Wed Jun 10 19:29:50 CST 2015.
    -->
    insert into t_g_project_private (id, user_name, project_code, 
      virtual_truck_url)
    values (#{id,jdbcType=CHAR}, #{userName,jdbcType=VARCHAR}, #{projectCode,jdbcType=VARCHAR}, 
      #{virtualTruckUrl,jdbcType=VARCHAR})
  </insert>
  <insert id="insertSelective" parameterType="cn.creditease.godzilla.model.ProjPrivate" >
    <!--
      WARNING - @mbggenerated
      This element is automatically generated by MyBatis Generator, do not modify.
      This element was generated on Wed Jun 10 19:29:50 CST 2015.
    -->
    insert into t_g_project_private
    <trim prefix="(" suffix=")" suffixOverrides="," >
      <if test="id != null" >
        id,
      </if>
      <if test="userName != null" >
        user_name,
      </if>
      <if test="projectCode != null" >
        project_code,
      </if>
      <if test="virtualTruckUrl != null" >
        virtual_truck_url,
      </if>
    </trim>
    <trim prefix="values (" suffix=")" suffixOverrides="," >
      <if test="id != null" >
        #{id,jdbcType=CHAR},
      </if>
      <if test="userName != null" >
        #{userName,jdbcType=VARCHAR},
      </if>
      <if test="projectCode != null" >
        #{projectCode,jdbcType=VARCHAR},
      </if>
      <if test="virtualTruckUrl != null" >
        #{virtualTruckUrl,jdbcType=VARCHAR},
      </if>
    </trim>
  </insert>
</mapper>